Workbook

Sheet Municipality Master
A1: Municipality | B1: State | C1: County | D1: Population | E1: Priority Tier | F1: Research Status | G1: Researcher | H1: Date Started | I1: Date Completed | J1: Has Existing Data | K1: Data Source
A2: Chicago | B2: IL | C2: Cook | D2: 2700000 | E2: A - High Priority | F2: Complete | J2: Yes | K2: AI Estimate (Not Verified)
A3: Aurora | B3: IL | C3: Kane/DuPage | D3: 197000 | E3: A - High Priority | F3: Complete | J3: Yes | K3: AI Estimate (Not Verified)
A4: Naperville | B4: IL | C4: DuPage/Will | D4: 149000 | E4: A - High Priority | F4: Complete | J4: Yes | K4: AI Estimate (Not Verified)
A5: Joliet | B5: IL | C5: Will | D5: 148000 | E5: A - High Priority | F5: Complete | J5: Yes | K5: AI Estimate (Not Verified)
A6: Rockford | B6: IL | C6: Winnebago | D6: 146000 | E6: A - High Priority | F6: Not Started | J6: No
A7: Springfield | B7: IL | C7: Sangamon | D7: 114000 | E7: A - High Priority | F7: Not Started | J7: No
A8: Elgin | B8: IL | C8: Kane/Cook | D8: 112000 | E8: A - High Priority | F8: Not Started | J8: No
A9: Peoria | B9: IL | C9: Peoria | D9: 110000 | E9: A - High Priority | F9: Not Started | J9: No
A10: Champaign | B10: IL | C10: Champaign | D10: 88000 | E10: A - High Priority | F10: Not Started | J10: No
A11: Waukegan | B11: IL | C11: Lake | D11: 87000 | E11: A - High Priority | F11: Complete | J11: Yes | K11: AI Estimate (Not Verified)
A12: Cicero | B12: IL | C12: Cook | D12: 84000 | E12: A - High Priority | F12: Complete | J12: Yes | K12: AI Estimate (Not Verified)
A13: Bloomington | B13: IL | C13: McLean | D13: 78000 | E13: A - High Priority | F13: Not Started | J13: No
A14: Arlington Heights | B14: IL | C14: Cook | D14: 76000 | E14: A - High Priority | F14: Complete | J14: Yes | K14: AI Estimate (Not Verified)
A15: Evanston | B15: IL | C15: Cook | D15: 74000 | E15: A - High Priority | F15: Complete | J15: Yes | K15: AI Estimate (Not Verified)
A16: Schaumburg | B16: IL | C16: Cook/DuPage | D16: 74000 | E16: A - High Priority | F16: Complete | J16: Yes | K16: AI Estimate (Not Verified)
A17: Bolingbrook | B17: IL | C17: Will/DuPage | D17: 73000 | E17: A - High Priority | F17: Complete | J17: Yes | K17: AI Estimate (Not Verified)
A18: Decatur | B18: IL | C18: Macon | D18: 70000 | E18: A - High Priority | F18: Not Started | J18: No
A19: Palatine | B19: IL | C19: Cook | D19: 68000 | E19: A - High Priority | F19: Complete | J19: Yes | K19: AI Estimate (Not Verified)
A20: Skokie | B20: IL | C20: Cook | D20: 65000 | E20: A - High Priority | F20: Complete | J20: Yes | K20: AI Estimate (Not Verified)
A21: Orland Park | B21: IL | C21: Cook | D21: 58000 | E21: A - High Priority | F21: Complete | J21: Yes | K21: AI Estimate (Not Verified)
A22: Des Plaines | B22: IL | C22: Cook | D22: 58000 | E22: A - High Priority | F22: Complete | J22: Yes | K22: AI Estimate (Not Verified)
A23: Tinley Park | B23: IL | C23: Cook | D23: 57000 | E23: A - High Priority | F23: Complete | J23: Yes | K23: AI Estimate (Not Verified)
A24: Oak Lawn | B24: IL | C24: Cook | D24: 57000 | E24: A - High Priority | F24: Not Started | J24: No
A25: Berwyn | B25: IL | C25: Cook | D25: 55000 | E25: A - High Priority | F25: Complete | J25: Yes | K25: AI Estimate (Not Verified)
A26: Mount Prospect | B26: IL | C26: Cook | D26: 54000 | E26: A - High Priority | F26: Complete | J26: Yes | K26: AI Estimate (Not Verified)
A27: Wheaton | B27: IL | C27: DuPage | D27: 53000 | E27: A - High Priority | F27: Complete | J27: Yes | K27: AI Estimate (Not Verified)
A28: Hoffman Estates | B28: IL | C28: Cook | D28: 52000 | E28: A - High Priority | F28: Complete | J28: Yes | K28: AI Estimate (Not Verified)
A29: Oak Park | B29: IL | C29: Cook | D29: 52000 | E29: A - High Priority | F29: Complete | J29: Yes | K29: AI Estimate (Not Verified)
A30: Normal | B30: IL | C30: McLean | D30: 52000 | E30: A - High Priority | F30: Not Started | J30: No
A31: Downers Grove | B31: IL | C31: DuPage | D31: 49000 | E31: A - High Priority | F31: Complete | J31: Yes | K31: AI Estimate (Not Verified)
A32: Glenview | B32: IL | C32: Cook | D32: 47000 | E32: A - High Priority | F32: Complete | J32: Yes | K32: AI Estimate (Not Verified)
A33: Elmhurst | B33: IL | C33: DuPage | D33: 46000 | E33: A - High Priority | F33: Complete | J33: Yes | K33: AI Estimate (Not Verified)
A34: Lombard | B34: IL | C34: DuPage | D34: 44000 | E34: A - High Priority | F34: Complete | J34: Yes | K34: AI Estimate (Not Verified)
A35: DeKalb | B35: IL | C35: DeKalb | D35: 44000 | E35: A - High Priority | F35: Not Started | J35: No
A36: Moline | B36: IL | C36: Rock Island | D36: 42000 | E36: A - High Priority | F36: Not Started | J36: No
A37: Belleville | B37: IL | C37: St. Clair | D37: 42000 | E37: A - High Priority | F37: Not Started | J37: No
A38: Plainfield | B38: IL | C38: Will | D38: 41000 | E38: A - High Priority | F38: Complete | J38: Yes | K38: AI Estimate (Not Verified)
A39: Bartlett | B39: IL | C39: Cook/DuPage | D39: 41000 | E39: A - High Priority | F39: Not Started | J39: No
A40: Buffalo Grove | B40: IL | C40: Lake/Cook | D40: 41000 | E40: A - High Priority | F40: Not Started | J40: No
A41: Carol Stream | B41: IL | C41: DuPage | D41: 40000 | E41: A - High Priority | F41: Complete | J41: Yes | K41: AI Estimate (Not Verified)
A42: Streamwood | B42: IL | C42: Cook | D42: 40000 | E42: A - High Priority | F42: Not Started | J42: No
A43: Quincy | B43: IL | C43: Adams | D43: 40000 | E43: A - High Priority | F43: Not Started | J43: No
A44: Romeoville | B44: IL | C44: Will | D44: 39000 | E44: A - High Priority | F44: Complete | J44: Yes | K44: AI Estimate (Not Verified)
A45: Crystal Lake | B45: IL | C45: McHenry | D45: 39000 | E45: A - High Priority | F45: Not Started | J45: No
A46: Wheeling | B46: IL | C46: Cook | D46: 38000 | E46: A - High Priority | F46: Not Started | J46: No
A47: Urbana | B47: IL | C47: Champaign | D47: 38000 | E47: A - High Priority | F47: Not Started | J47: No
A48: Park Ridge | B48: IL | C48: Cook | D48: 37000 | E48: A - High Priority | F48: Complete | J48: Yes | K48: AI Estimate (Not Verified)
A49: Hanover Park | B49: IL | C49: Cook/DuPage | D49: 37000 | E49: A - High Priority | F49: Not Started | J49: No
A50: Carpentersville | B50: IL | C50: Kane | D50: 37000 | E50: A - High Priority | F50: Not Started | J50: No
A51: Oswego | B51: IL | C51: Kendall | D51: 37000 | E51: A - High Priority | F51: Not Started | J51: No
A52: Rock Island | B52: IL | C52: Rock Island | D52: 37000 | E52: A - High Priority | F52: Not Started | J52: No
A53: Addison | B53: IL | C53: DuPage | D53: 36000 | E53: A - High Priority | F53: Complete | J53: Yes | K53: AI Estimate (Not Verified)
A54: Calumet City | B54: IL | C54: Cook | D54: 36000 | E54: A - High Priority | F54: Not Started | J54: No
A55: Glendale Heights | B55: IL | C55: DuPage | D55: 34000 | E55: A - High Priority | F55: Complete | J55: Yes | K55: AI Estimate (Not Verified)
A56: Northbrook | B56: IL | C56: Cook | D56: 33000 | E56: A - High Priority | F56: Complete | J56: Yes | K56: AI Estimate (Not Verified)
A57: St. Charles | B57: IL | C57: Kane/DuPage | D57: 33000 | E57: A - High Priority | F57: Not Started | J57: No
A58: Woodridge | B58: IL | C58: DuPage | D58: 33000 | E58: A - High Priority | F58: Not Started | J58: No
A59: Pekin | B59: IL | C59: Tazewell | D59: 33000 | E59: A - High Priority | F59: Not Started | J59: No
A60: Elk Grove Village | B60: IL | C60: Cook | D60: 32000 | E60: A - High Priority | F60: Complete | J60: Yes | K60: AI Estimate (Not Verified)
A61: Mundelein | B61: IL | C61: Lake | D61: 31000 | E61: A - High Priority | F61: Complete | J61: Yes | K61: AI Estimate (Not Verified)
A62: Gurnee | B62: IL | C62: Lake | D62: 31000 | E62: A - High Priority | F62: Not Started | J62: No
A63: Lake in the Hills | B63: IL | C63: McHenry | D63: 30000 | E63: A - High Priority | F63: Not Started | J63: No
A64: Highland Park | B64: IL | C64: Lake | D64: 30000 | E64: A - High Priority | F64: Complete | J64: Yes | K64: AI Estimate (Not Verified)
A65: Niles | B65: IL | C65: Cook | D65: 30000 | E65: A - High Priority | F65: Not Started | J65: No
A66: Algonquin | B66: IL | C66: McHenry/Kane | D66: 30000 | E66: A - High Priority | F66: Not Started | J66: No
A67: Danville | B67: IL | C67: Vermilion | D67: 30000 | E67: A - High Priority | F67: Not Started | J67: No
A68: Galesburg | B68: IL | C68: Knox | D68: 30000 | E68: A - High Priority | F68: Not Started | J68: No
A69: O'Fallon | B69: IL | C69: St. Clair | D69: 30000 | E69: A - High Priority | F69: Not Started | J69: No
A70: Wilmette | B70: IL | C70: Cook | D70: 28000 | E70: A - High Priority | F70: Complete | J70: Yes | K70: AI Estimate (Not Verified)
A71: Oak Forest | B71: IL | C71: Cook | D71: 28000 | E71: A - High Priority | F71: Complete | J71: Yes | K71: AI Estimate (Not Verified)
A72: Granite City | B72: IL | C72: Madison | D72: 28000 | E72: A - High Priority | F72: Not Started | J72: No
A73: Huntley | B73: IL | C73: McHenry/Kane | D73: 27000 | E73: A - High Priority | F73: Not Started | J73: No
A74: McHenry | B74: IL | C74: McHenry | D74: 27000 | E74: A - High Priority | F74: Not Started | J74: No
A75: New Lenox | B75: IL | C75: Will | D75: 27000 | E75: A - High Priority | F75: Not Started | J75: No
A76: Batavia | B76: IL | C76: Kane | D76: 26000 | E76: A - High Priority | F76: Not Started | J76: No
A77: Vernon Hills | B77: IL | C77: Lake | D77: 26000 | E77: A - High Priority | F77: Not Started | J77: No
A78: Alton | B78: IL | C78: Madison | D78: 26000 | E78: A - High Priority | F78: Not Started | J78: No
A79: Lockport | B79: IL | C79: Will | D79: 25000 | E79: A - High Priority | F79: Complete | J79: Yes | K79: AI Estimate (Not Verified)
A80: Woodstock | B80: IL | C80: McHenry | D80: 25000 | E80: A - High Priority | F80: Not Started | J80: No
A81: Collinsville | B81: IL | C81: Madison | D81: 25000 | E81: A - High Priority | F81: Not Started | J81: No
A82: Edwardsville | B82: IL | C82: Madison | D82: 25000 | E82: A - High Priority | F82: Not Started | J82: No
A83: Westmont | B83: IL | C83: DuPage | D83: 24000 | E83: A - High Priority | F83: Complete | J83: Yes | K83: AI Estimate (Not Verified)
A84: Maywood | B84: IL | C84: Cook | D84: 24000 | E84: A - High Priority | F84: Not Started | J84: No
A85: Rolling Meadows | B85: IL | C85: Cook | D85: 24000 | E85: A - High Priority | F85: Complete | J85: Yes | K85: AI Estimate (Not Verified)
A86: Morton Grove | B86: IL | C86: Cook | D86: 23000 | E86: A - High Priority | F86: Not Started | J86: No
A87: Lisle | B87: IL | C87: DuPage | D87: 23000 | E87: A - High Priority | F87: Not Started | J87: No
A88: Roselle | B88: IL | C88: DuPage | D88: 23000 | E88: A - High Priority | F88: Not Started | J88: No
A89: Blue Island | B89: IL | C89: Cook | D89: 23000 | E89: A - High Priority | F89: Complete | J89: Yes | K89: AI Estimate (Not Verified)
A90: Melrose Park | B90: IL | C90: Cook | D90: 23000 | E90: A - High Priority | F90: Complete | J90: Yes | K90: AI Estimate (Not Verified)
A91: Geneva | B91: IL | C91: Kane | D91: 22000 | E91: A - High Priority | F91: Not Started | J91: No
A92: Yorkville | B92: IL | C92: Kendall | D92: 22000 | E92: A - High Priority | F92: Not Started | J92: No
A93: Darien | B93: IL | C93: DuPage | D93: 22000 | E93: A - High Priority | F93: Complete | J93: Yes | K93: AI Estimate (Not Verified)
A94: Villa Park | B94: IL | C94: DuPage | D94: 22000 | E94: A - High Priority | F94: Complete | J94: Yes | K94: AI Estimate (Not Verified)
A95: Bloomingdale | B95: IL | C95: DuPage | D95: 22000 | E95: A - High Priority | F95: Complete | J95: Yes | K95: AI Estimate (Not Verified)
A96: Carbondale | B96: IL | C96: Jackson | D96: 22000 | E96: A - High Priority | F96: Not Started | J96: No
A97: Homer Glen | B97: IL | C97: Will | D97: 21500 | E97: A - High Priority | F97: Complete | J97: Yes | K97: AI Estimate (Not Verified)
A98: Grayslake | B98: IL | C98: Lake | D98: 21000 | E98: A - High Priority | F98: Complete | J98: Yes | K98: AI Estimate (Not Verified)
A99: Bensenville | B99: IL | C99: DuPage | D99: 21000 | E99: A - High Priority | F99: Complete | J99: Yes | K99: AI Estimate (Not Verified)
A100: Crest Hill | B100: IL | C100: Will | D100: 21000 | E100: A - High Priority | F100: Not Started | J100: No
...

Sheet Zoning Research
A1: Municipality | B1: State | C1: DT Zones Allowed | D1: DT Approval Pathway | E1: CW Zones Allowed | F1: CW Approval Pathway | G1: Zoning Code Score (0-20) | H1: Stacking Req (# cars) | I1: Lot Size Min (sq ft) | J1: Front Setback (ft) | K1: Side Setback (ft) | L1: Rear Setback (ft) | M1: Proximity Restrictions | N1: Hours Limits | O1: Traffic Study Req? | P1: Arch Review Req? | Q1: Site Req Score (0-20) | R1: Recent Approvals (3yr) | S1: Recent Denials (3yr) | T1: Avg Timeline (months) | U1: Est Approval Cost ($) | V1: Approval Score (0-20) | W1: # Existing Carwashes | X1: # DT Coffee Shops | Y1: # DT QSR Total | Z1: Saturation Score (0-20) | AA1: Board Receptivity | AB1: Moratorium? | AC1: Pending Ordinance Changes? | AD1: Notes | AE1: Political Score (0-20) | AF1: COMPOSITE SCORE | AG1: Override Score | AH1: Override Reason | AI1: Source URL 1 | AJ1: Source URL 2 | AK1: Confidence | AL1: Last Updated
A2: Chicago | B2: IL | G2: 18 | Q2: 18 | V2: 18 | Z2: 18 | AE2: 18 | AF2: =IF(AG2<>"",AG2,SUM(G2,Q2,V2,Z2,AE2)) -> 90 | AI2: AI Estimate
A3: Aurora | B3: IL | G3: 20 | Q3: 20 | V3: 20 | Z3: 20 | AE3: 20 | AF3: =IF(AG3<>"",AG3,SUM(G3,Q3,V3,Z3,AE3)) -> 100 | AI3: AI Estimate
A4: Naperville | B4: IL | D4: Conditional Use | F4: Conditional Use | G4: 12 | H4: 10 | Q4: 8 | R4: 1 | S4: 1 | V4: 5 | W4: 3 | X4: 2 | Z4: 8 | AA4: Hostile | AD4: City blocked Dutch Bros on Napier Blvd due to 7 Brew saturation at 1203 Iroquois. Board actively discouraging new DT coffee. | AE4: 5 | AF4: =IF(AG4<>"",AG4,SUM(G4,Q4,V4,Z4,AE4)) -> 38 | AI4: High
A5: Joliet | B5: IL | G5: 20 | Q5: 20 | V5: 20 | Z5: 20 | AE5: 20 | AF5: =IF(AG5<>"",AG5,SUM(G5,Q5,V5,Z5,AE5)) -> 100 | AI5: AI Estimate
A6: Rockford | B6: IL | AF6: =IF(AG6<>"",AG6,SUM(G6,Q6,V6,Z6,AE6)) -> 0
A7: Springfield | B7: IL | AF7: =IF(AG7<>"",AG7,SUM(G7,Q7,V7,Z7,AE7)) -> 0
A8: Elgin | B8: IL | AF8: =IF(AG8<>"",AG8,SUM(G8,Q8,V8,Z8,AE8)) -> 0
A9: Peoria | B9: IL | AF9: =IF(AG9<>"",AG9,SUM(G9,Q9,V9,Z9,AE9)) -> 0
A10: Champaign | B10: IL | AF10: =IF(AG10<>"",AG10,SUM(G10,Q10,V10,Z10,AE10)) -> 0
A11: Waukegan | B11: IL | G11: 20 | Q11: 20 | V11: 20 | Z11: 20 | AE11: 20 | AF11: =IF(AG11<>"",AG11,SUM(G11,Q11,V11,Z11,AE11)) -> 100 | AI11: AI Estimate
A12: Cicero | B12: IL | G12: 20 | Q12: 20 | V12: 20 | Z12: 20 | AE12: 20 | AF12: =IF(AG12<>"",AG12,SUM(G12,Q12,V12,Z12,AE12)) -> 100 | AI12: AI Estimate
A13: Bloomington | B13: IL | AF13: =IF(AG13<>"",AG13,SUM(G13,Q13,V13,Z13,AE13)) -> 0
A14: Arlington Heights | B14: IL | G14: 16 | Q14: 16 | V14: 16 | Z14: 16 | AE14: 16 | AF14: =IF(AG14<>"",AG14,SUM(G14,Q14,V14,Z14,AE14)) -> 80 | AI14: AI Estimate
A15: Evanston | B15: IL | G15: 16 | Q15: 16 | V15: 16 | Z15: 16 | AE15: 16 | AF15: =IF(AG15<>"",AG15,SUM(G15,Q15,V15,Z15,AE15)) -> 80 | AI15: AI Estimate
A16: Schaumburg | B16: IL | G16: 14 | Q16: 14 | V16: 14 | Z16: 14 | AE16: 14 | AF16: =IF(AG16<>"",AG16,SUM(G16,Q16,V16,Z16,AE16)) -> 70 | AI16: AI Estimate
A17: Bolingbrook | B17: IL | G17: 20 | Q17: 20 | V17: 20 | Z17: 20 | AE17: 20 | AF17: =IF(AG17<>"",AG17,SUM(G17,Q17,V17,Z17,AE17)) -> 100 | AI17: AI Estimate
A18: Decatur | B18: IL | AF18: =IF(AG18<>"",AG18,SUM(G18,Q18,V18,Z18,AE18)) -> 0
A19: Palatine | B19: IL | G19: 18 | Q19: 18 | V19: 18 | Z19: 18 | AE19: 18 | AF19: =IF(AG19<>"",AG19,SUM(G19,Q19,V19,Z19,AE19)) -> 90 | AI19: AI Estimate
A20: Skokie | B20: IL | G20: 18 | Q20: 18 | V20: 18 | Z20: 18 | AE20: 18 | AF20: =IF(AG20<>"",AG20,SUM(G20,Q20,V20,Z20,AE20)) -> 90 | AI20: AI Estimate
A21: Orland Park | B21: IL | G21: 18 | Q21: 18 | V21: 18 | Z21: 18 | AE21: 18 | AF21: =IF(AG21<>"",AG21,SUM(G21,Q21,V21,Z21,AE21)) -> 90 | AI21: AI Estimate
A22: Des Plaines | B22: IL | G22: 20 | Q22: 20 | V22: 20 | Z22: 20 | AE22: 20 | AF22: =IF(AG22<>"",AG22,SUM(G22,Q22,V22,Z22,AE22)) -> 100 | AI22: AI Estimate
A23: Tinley Park | B23: IL | G23: 20 | Q23: 20 | V23: 20 | Z23: 20 | AE23: 20 | AF23: =IF(AG23<>"",AG23,SUM(G23,Q23,V23,Z23,AE23)) -> 100 | AI23: AI Estimate
A24: Oak Lawn | B24: IL | AF24: =IF(AG24<>"",AG24,SUM(G24,Q24,V24,Z24,AE24)) -> 0
A25: Berwyn | B25: IL | G25: 20 | Q25: 20 | V25: 20 | Z25: 20 | AE25: 20 | AF25: =IF(AG25<>"",AG25,SUM(G25,Q25,V25,Z25,AE25)) -> 100 | AI25: AI Estimate
A26: Mount Prospect | B26: IL | G26: 18 | Q26: 18 | V26: 18 | Z26: 18 | AE26: 18 | AF26: =IF(AG26<>"",AG26,SUM(G26,Q26,V26,Z26,AE26)) -> 90 | AI26: AI Estimate
A27: Wheaton | B27: IL | G27: 18 | Q27: 18 | V27: 18 | Z27: 18 | AE27: 18 | AF27: =IF(AG27<>"",AG27,SUM(G27,Q27,V27,Z27,AE27)) -> 90 | AI27: AI Estimate
A28: Hoffman Estates | B28: IL | G28: 18 | Q28: 18 | V28: 18 | Z28: 18 | AE28: 18 | AF28: =IF(AG28<>"",AG28,SUM(G28,Q28,V28,Z28,AE28)) -> 90 | AI28: AI Estimate
A29: Oak Park | B29: IL | G29: 16 | Q29: 16 | V29: 16 | Z29: 16 | AE29: 16 | AF29: =IF(AG29<>"",AG29,SUM(G29,Q29,V29,Z29,AE29)) -> 80 | AI29: AI Estimate
A30: Normal | B30: IL | AF30: =IF(AG30<>"",AG30,SUM(G30,Q30,V30,Z30,AE30)) -> 0
A31: Downers Grove | B31: IL | G31: 16 | Q31: 16 | V31: 16 | Z31: 16 | AE31: 16 | AF31: =IF(AG31<>"",AG31,SUM(G31,Q31,V31,Z31,AE31)) -> 80 | AI31: AI Estimate
A32: Glenview | B32: IL | G32: 18 | Q32: 18 | V32: 18 | Z32: 18 | AE32: 18 | AF32: =IF(AG32<>"",AG32,SUM(G32,Q32,V32,Z32,AE32)) -> 90 | AI32: AI Estimate
A33: Elmhurst | B33: IL | G33: 18 | Q33: 18 | V33: 18 | Z33: 18 | AE33: 18 | AF33: =IF(AG33<>"",AG33,SUM(G33,Q33,V33,Z33,AE33)) -> 90 | AI33: AI Estimate
A34: Lombard | B34: IL | G34: 18 | Q34: 18 | V34: 18 | Z34: 18 | AE34: 18 | AF34: =IF(AG34<>"",AG34,SUM(G34,Q34,V34,Z34,AE34)) -> 90 | AI34: AI Estimate
A35: DeKalb | B35: IL | AF35: =IF(AG35<>"",AG35,SUM(G35,Q35,V35,Z35,AE35)) -> 0
A36: Moline | B36: IL | AF36: =IF(AG36<>"",AG36,SUM(G36,Q36,V36,Z36,AE36)) -> 0
A37: Belleville | B37: IL | AF37: =IF(AG37<>"",AG37,SUM(G37,Q37,V37,Z37,AE37)) -> 0
A38: Plainfield | B38: IL | G38: 20 | Q38: 20 | V38: 20 | Z38: 20 | AE38: 20 | AF38: =IF(AG38<>"",AG38,SUM(G38,Q38,V38,Z38,AE38)) -> 100 | AI38: AI Estimate
A39: Bartlett | B39: IL | AF39: =IF(AG39<>"",AG39,SUM(G39,Q39,V39,Z39,AE39)) -> 0
A40: Buffalo Grove | B40: IL | AF40: =IF(AG40<>"",AG40,SUM(G40,Q40,V40,Z40,AE40)) -> 0
A41: Carol Stream | B41: IL | G41: 20 | Q41: 20 | V41: 20 | Z41: 20 | AE41: 20 | AF41: =IF(AG41<>"",AG41,SUM(G41,Q41,V41,Z41,AE41)) -> 100 | AI41: AI Estimate
A42: Streamwood | B42: IL | AF42: =IF(AG42<>"",AG42,SUM(G42,Q42,V42,Z42,AE42)) -> 0
A43: Quincy | B43: IL | AF43: =IF(AG43<>"",AG43,SUM(G43,Q43,V43,Z43,AE43)) -> 0
A44: Romeoville | B44: IL | G44: 20 | Q44: 20 | V44: 20 | Z44: 20 | AE44: 20 | AF44: =IF(AG44<>"",AG44,SUM(G44,Q44,V44,Z44,AE44)) -> 100 | AI44: AI Estimate
A45: Crystal Lake | B45: IL | AF45: =IF(AG45<>"",AG45,SUM(G45,Q45,V45,Z45,AE45)) -> 0
A46: Wheeling | B46: IL | AF46: =IF(AG46<>"",AG46,SUM(G46,Q46,V46,Z46,AE46)) -> 0
A47: Urbana | B47: IL | AF47: =IF(AG47<>"",AG47,SUM(G47,Q47,V47,Z47,AE47)) -> 0
A48: Park Ridge | B48: IL | G48: 16 | Q48: 16 | V48: 16 | Z48: 16 | AE48: 16 | AF48: =IF(AG48<>"",AG48,SUM(G48,Q48,V48,Z48,AE48)) -> 80 | AI48: AI Estimate
A49: Hanover Park | B49: IL | AF49: =IF(AG49<>"",AG49,SUM(G49,Q49,V49,Z49,AE49)) -> 0
A50: Carpentersville | B50: IL | AF50: =IF(AG50<>"",AG50,SUM(G50,Q50,V50,Z50,AE50)) -> 0
A51: Oswego | B51: IL | AF51: =IF(AG51<>"",AG51,SUM(G51,Q51,V51,Z51,AE51)) -> 0
A52: Rock Island | B52: IL | AF52: =IF(AG52<>"",AG52,SUM(G52,Q52,V52,Z52,AE52)) -> 0
A53: Addison | B53: IL | G53: 20 | Q53: 20 | V53: 20 | Z53: 20 | AE53: 20 | AF53: =IF(AG53<>"",AG53,SUM(G53,Q53,V53,Z53,AE53)) -> 100 | AI53: AI Estimate
A54: Calumet City | B54: IL | AF54: =IF(AG54<>"",AG54,SUM(G54,Q54,V54,Z54,AE54)) -> 0
A55: Glendale Heights | B55: IL | G55: 20 | Q55: 20 | V55: 20 | Z55: 20 | AE55: 20 | AF55: =IF(AG55<>"",AG55,SUM(G55,Q55,V55,Z55,AE55)) -> 100 | AI55: AI Estimate
A56: Northbrook | B56: IL | G56: 18 | Q56: 18 | V56: 18 | Z56: 18 | AE56: 18 | AF56: =IF(AG56<>"",AG56,SUM(G56,Q56,V56,Z56,AE56)) -> 90 | AI56: AI Estimate
A57: St. Charles | B57: IL | AF57: =IF(AG57<>"",AG57,SUM(G57,Q57,V57,Z57,AE57)) -> 0
A58: Woodridge | B58: IL | AF58: =IF(AG58<>"",AG58,SUM(G58,Q58,V58,Z58,AE58)) -> 0
A59: Pekin | B59: IL | AF59: =IF(AG59<>"",AG59,SUM(G59,Q59,V59,Z59,AE59)) -> 0
A60: Elk Grove Village | B60: IL | G60: 20 | Q60: 20 | V60: 20 | Z60: 20 | AE60: 20 | AF60: =IF(AG60<>"",AG60,SUM(G60,Q60,V60,Z60,AE60)) -> 100 | AI60: AI Estimate
A61: Mundelein | B61: IL | G61: 20 | Q61: 20 | V61: 20 | Z61: 20 | AE61: 20 | AF61: =IF(AG61<>"",AG61,SUM(G61,Q61,V61,Z61,AE61)) -> 100 | AI61: AI Estimate
A62: Gurnee | B62: IL | AF62: =IF(AG62<>"",AG62,SUM(G62,Q62,V62,Z62,AE62)) -> 0
A63: Lake in the Hills | B63: IL | AF63: =IF(AG63<>"",AG63,SUM(G63,Q63,V63,Z63,AE63)) -> 0
A64: Highland Park | B64: IL | G64: 16 | Q64: 16 | V64: 16 | Z64: 16 | AE64: 16 | AF64: =IF(AG64<>"",AG64,SUM(G64,Q64,V64,Z64,AE64)) -> 80 | AI64: AI Estimate
A65: Niles | B65: IL | AF65: =IF(AG65<>"",AG65,SUM(G65,Q65,V65,Z65,AE65)) -> 0
A66: Algonquin | B66: IL | AF66: =IF(AG66<>"",AG66,SUM(G66,Q66,V66,Z66,AE66)) -> 0
A67: Danville | B67: IL | AF67: =IF(AG67<>"",AG67,SUM(G67,Q67,V67,Z67,AE67)) -> 0
A68: Galesburg | B68: IL | AF68: =IF(AG68<>"",AG68,SUM(G68,Q68,V68,Z68,AE68)) -> 0
A69: O'Fallon | B69: IL | AF69: =IF(AG69<>"",AG69,SUM(G69,Q69,V69,Z69,AE69)) -> 0
A70: Wilmette | B70: IL | G70: 16 | Q70: 16 | V70: 16 | Z70: 16 | AE70: 16 | AF70: =IF(AG70<>"",AG70,SUM(G70,Q70,V70,Z70,AE70)) -> 80 | AI70: AI Estimate
A71: Oak Forest | B71: IL | G71: 20 | Q71: 20 | V71: 20 | Z71: 20 | AE71: 20 | AF71: =IF(AG71<>"",AG71,SUM(G71,Q71,V71,Z71,AE71)) -> 100 | AI71: AI Estimate
A72: Granite City | B72: IL | AF72: =IF(AG72<>"",AG72,SUM(G72,Q72,V72,Z72,AE72)) -> 0
A73: Huntley | B73: IL | AF73: =IF(AG73<>"",AG73,SUM(G73,Q73,V73,Z73,AE73)) -> 0
A74: McHenry | B74: IL | AF74: =IF(AG74<>"",AG74,SUM(G74,Q74,V74,Z74,AE74)) -> 0
A75: New Lenox | B75: IL | AF75: =IF(AG75<>"",AG75,SUM(G75,Q75,V75,Z75,AE75)) -> 0
A76: Batavia | B76: IL | AF76: =IF(AG76<>"",AG76,SUM(G76,Q76,V76,Z76,AE76)) -> 0
A77: Vernon Hills | B77: IL | AF77: =IF(AG77<>"",AG77,SUM(G77,Q77,V77,Z77,AE77)) -> 0
A78: Alton | B78: IL | AF78: =IF(AG78<>"",AG78,SUM(G78,Q78,V78,Z78,AE78)) -> 0
A79: Lockport | B79: IL | G79: 20 | Q79: 20 | V79: 20 | Z79: 20 | AE79: 20 | AF79: =IF(AG79<>"",AG79,SUM(G79,Q79,V79,Z79,AE79)) -> 100 | AI79: AI Estimate
A80: Woodstock | B80: IL | AF80: =IF(AG80<>"",AG80,SUM(G80,Q80,V80,Z80,AE80)) -> 0
A81: Collinsville | B81: IL | AF81: =IF(AG81<>"",AG81,SUM(G81,Q81,V81,Z81,AE81)) -> 0
A82: Edwardsville | B82: IL | AF82: =IF(AG82<>"",AG82,SUM(G82,Q82,V82,Z82,AE82)) -> 0
A83: Westmont | B83: IL | G83: 16 | Q83: 16 | V83: 16 | Z83: 16 | AE83: 16 | AF83: =IF(AG83<>"",AG83,SUM(G83,Q83,V83,Z83,AE83)) -> 80 | AI83: AI Estimate
A84: Maywood | B84: IL | AF84: =IF(AG84<>"",AG84,SUM(G84,Q84,V84,Z84,AE84)) -> 0
A85: Rolling Meadows | B85: IL | G85: 18 | Q85: 18 | V85: 18 | Z85: 18 | AE85: 18 | AF85: =IF(AG85<>"",AG85,SUM(G85,Q85,V85,Z85,AE85)) -> 90 | AI85: AI Estimate
A86: Morton Grove | B86: IL | AF86: =IF(AG86<>"",AG86,SUM(G86,Q86,V86,Z86,AE86)) -> 0
A87: Lisle | B87: IL | AF87: =IF(AG87<>"",AG87,SUM(G87,Q87,V87,Z87,AE87)) -> 0
A88: Roselle | B88: IL | AF88: =IF(AG88<>"",AG88,SUM(G88,Q88,V88,Z88,AE88)) -> 0
A89: Blue Island | B89: IL | G89: 20 | Q89: 20 | V89: 20 | Z89: 20 | AE89: 20 | AF89: =IF(AG89<>"",AG89,SUM(G89,Q89,V89,Z89,AE89)) -> 100 | AI89: AI Estimate
A90: Melrose Park | B90: IL | G90: 20 | Q90: 20 | V90: 20 | Z90: 20 | AE90: 20 | AF90: =IF(AG90<>"",AG90,SUM(G90,Q90,V90,Z90,AE90)) -> 100 | AI90: AI Estimate
A91: Geneva | B91: IL | AF91: =IF(AG91<>"",AG91,SUM(G91,Q91,V91,Z91,AE91)) -> 0
A92: Yorkville | B92: IL | AF92: =IF(AG92<>"",AG92,SUM(G92,Q92,V92,Z92,AE92)) -> 0
A93: Darien | B93: IL | G93: 16 | Q93: 16 | V93: 16 | Z93: 16 | AE93: 16 | AF93: =IF(AG93<>"",AG93,SUM(G93,Q93,V93,Z93,AE93)) -> 80 | AI93: AI Estimate
A94: Villa Park | B94: IL | G94: 20 | Q94: 20 | V94: 20 | Z94: 20 | AE94: 20 | AF94: =IF(AG94<>"",AG94,SUM(G94,Q94,V94,Z94,AE94)) -> 100 | AI94: AI Estimate
A95: Bloomingdale | B95: IL | G95: 20 | Q95: 20 | V95: 20 | Z95: 20 | AE95: 20 | AF95: =IF(AG95<>"",AG95,SUM(G95,Q95,V95,Z95,AE95)) -> 100 | AI95: AI Estimate
A96: Carbondale | B96: IL | AF96: =IF(AG96<>"",AG96,SUM(G96,Q96,V96,Z96,AE96)) -> 0
A97: Homer Glen | B97: IL | G97: 20 | Q97: 20 | V97: 20 | Z97: 20 | AE97: 20 | AF97: =IF(AG97<>"",AG97,SUM(G97,Q97,V97,Z97,AE97)) -> 100 | AI97: AI Estimate
A98: Grayslake | B98: IL | G98: 20 | Q98: 20 | V98: 20 | Z98: 20 | AE98: 20 | AF98: =IF(AG98<>"",AG98,SUM(G98,Q98,V98,Z98,AE98)) -> 100 | AI98: AI Estimate
A99: Bensenville | B99: IL | G99: 20 | Q99: 20 | V99: 20 | Z99: 20 | AE99: 20 | AF99: =IF(AG99<>"",AG99,SUM(G99,Q99,V99,Z99,AE99)) -> 100 | AI99: AI Estimate
A100: Crest Hill | B100: IL | AF100: =IF(AG100<>"",AG100,SUM(G100,Q100,V100,Z100,AE100)) -> 0
...

Sheet Approval History
A1: Municipality | B1: State | C1: Project Name | D1: Applicant/Chain | E1: Use Type | F1: Date | G1: Outcome | H1: Conditions/Notes | I1: Source URL | J1: Entered By
A2: Naperville | B2: IL | C2: 7 Brew Coffee | D2: 7 Brew | E2: Drive-Thru Coffee | F2: 2024 | G2: Approved w/ Conditions | H2: 1203 Iroquois Road. Approved with extensive conditions. | J2: T. Ryan
A3: Naperville | B3: IL | C3: Dutch Bros Coffee | D3: Dutch Bros | E3: Drive-Thru Coffee | F3: 2025 | G3: Denied | H3: Napier Boulevard location. City not supportive due to 7 Brew saturation. | J3: T. Ryan

Sheet Competitive Landscape
A1: Municipality | B1: State | C1: Business Name | D1: Address | E1: Type | F1: Chain/Independent | G1: Year Opened (est) | H1: Source/Notes
A2: Naperville | B2: IL | C2: 7 Brew Coffee | D2: 1203 Iroquois Road | E2: Drive-Thru Coffee | F2: Chain (Blackstone-backed) | G2: 2024 | H2: Direct competitor. Blackstone growth equity investment Feb 2024. 600+ locations.

Sheet Score Calculator
A1: Municipality | B1: State | C1: Population | D1: Tier | E1: Zoning (0-20) | F1: Site Req (0-20) | G1: Approval (0-20) | H1: Saturation (0-20) | I1: Political (0-20) | J1: COMPOSITE | K1: Override | L1: Override Reason | M1: Confidence | N1: CW Score (old) | O1: DT Score (old) | P1: Delta
A2: Chicago | B2: IL | C2: 2700000 | D2: A | E2: ='Zoning Research'!G2 -> 18 | F2: ='Zoning Research'!Q2 -> 18 | G2: ='Zoning Research'!V2 -> 18 | H2: ='Zoning Research'!Z2 -> 18 | I2: ='Zoning Research'!AE2 -> 18 | J2: ='Zoning Research'!AF2 -> 90 | K2: ='Zoning Research'!AG2 -> 0 | L2: ='Zoning Research'!AH2 -> 0 | M2: ='Zoning Research'!AI2 -> AI Estimate | N2: 95 | O2: 85 | P2: =IF(J2="","",J2-AVERAGE(N2,O2)) -> 0
A3: Aurora | B3: IL | C3: 197000 | D3: A | E3: ='Zoning Research'!G3 -> 20 | F3: ='Zoning Research'!Q3 -> 20 | G3: ='Zoning Research'!V3 -> 20 | H3: ='Zoning Research'!Z3 -> 20 | I3: ='Zoning Research'!AE3 -> 20 | J3: ='Zoning Research'!AF3 -> 100 | K3: ='Zoning Research'!AG3 -> 0 | L3: ='Zoning Research'!AH3 -> 0 | M3: ='Zoning Research'!AI3 -> AI Estimate | N3: 100 | O3: 100 | P3: =IF(J3="","",J3-AVERAGE(N3,O3)) -> 0
A4: Naperville | B4: IL | C4: 149000 | D4: A | E4: ='Zoning Research'!G4 -> 12 | F4: ='Zoning Research'!Q4 -> 8 | G4: ='Zoning Research'!V4 -> 5 | H4: ='Zoning Research'!Z4 -> 8 | I4: ='Zoning Research'!AE4 -> 5 | J4: ='Zoning Research'!AF4 -> 38 | K4: ='Zoning Research'!AG4 -> 0 | L4: ='Zoning Research'!AH4 -> 0 | M4: ='Zoning Research'!AI4 -> High | N4: 75 | O4: 65 | P4: =IF(J4="","",J4-AVERAGE(N4,O4)) -> -32
A5: Joliet | B5: IL | C5: 148000 | D5: A | E5: ='Zoning Research'!G5 -> 20 | F5: ='Zoning Research'!Q5 -> 20 | G5: ='Zoning Research'!V5 -> 20 | H5: ='Zoning Research'!Z5 -> 20 | I5: ='Zoning Research'!AE5 -> 20 | J5: ='Zoning Research'!AF5 -> 100 | K5: ='Zoning Research'!AG5 -> 0 | L5: ='Zoning Research'!AH5 -> 0 | M5: ='Zoning Research'!AI5 -> AI Estimate | N5: 100 | O5: 100 | P5: =IF(J5="","",J5-AVERAGE(N5,O5)) -> 0
A6: Rockford | B6: IL | C6: 146000 | D6: A | E6: ='Zoning Research'!G6 -> 0 | F6: ='Zoning Research'!Q6 -> 0 | G6: ='Zoning Research'!V6 -> 0 | H6: ='Zoning Research'!Z6 -> 0 | I6: ='Zoning Research'!AE6 -> 0 | J6: ='Zoning Research'!AF6 -> 0 | K6: ='Zoning Research'!AG6 -> 0 | L6: ='Zoning Research'!AH6 -> 0 | M6: ='Zoning Research'!AI6 -> 0
A7: Springfield | B7: IL | C7: 114000 | D7: A | E7: ='Zoning Research'!G7 -> 0 | F7: ='Zoning Research'!Q7 -> 0 | G7: ='Zoning Research'!V7 -> 0 | H7: ='Zoning Research'!Z7 -> 0 | I7: ='Zoning Research'!AE7 -> 0 | J7: ='Zoning Research'!AF7 -> 0 | K7: ='Zoning Research'!AG7 -> 0 | L7: ='Zoning Research'!AH7 -> 0 | M7: ='Zoning Research'!AI7 -> 0
A8: Elgin | B8: IL | C8: 112000 | D8: A | E8: ='Zoning Research'!G8 -> 0 | F8: ='Zoning Research'!Q8 -> 0 | G8: ='Zoning Research'!V8 -> 0 | H8: ='Zoning Research'!Z8 -> 0 | I8: ='Zoning Research'!AE8 -> 0 | J8: ='Zoning Research'!AF8 -> 0 | K8: ='Zoning Research'!AG8 -> 0 | L8: ='Zoning Research'!AH8 -> 0 | M8: ='Zoning Research'!AI8 -> 0
A9: Peoria | B9: IL | C9: 110000 | D9: A | E9: ='Zoning Research'!G9 -> 0 | F9: ='Zoning Research'!Q9 -> 0 | G9: ='Zoning Research'!V9 -> 0 | H9: ='Zoning Research'!Z9 -> 0 | I9: ='Zoning Research'!AE9 -> 0 | J9: ='Zoning Research'!AF9 -> 0 | K9: ='Zoning Research'!AG9 -> 0 | L9: ='Zoning Research'!AH9 -> 0 | M9: ='Zoning Research'!AI9 -> 0
A10: Champaign | B10: IL | C10: 88000 | D10: A | E10: ='Zoning Research'!G10 -> 0 | F10: ='Zoning Research'!Q10 -> 0 | G10: ='Zoning Research'!V10 -> 0 | H10: ='Zoning Research'!Z10 -> 0 | I10: ='Zoning Research'!AE10 -> 0 | J10: ='Zoning Research'!AF10 -> 0 | K10: ='Zoning Research'!AG10 -> 0 | L10: ='Zoning Research'!AH10 -> 0 | M10: ='Zoning Research'!AI10 -> 0
A11: Waukegan | B11: IL | C11: 87000 | D11: A | E11: ='Zoning Research'!G11 -> 20 | F11: ='Zoning Research'!Q11 -> 20 | G11: ='Zoning Research'!V11 -> 20 | H11: ='Zoning Research'!Z11 -> 20 | I11: ='Zoning Research'!AE11 -> 20 | J11: ='Zoning Research'!AF11 -> 100 | K11: ='Zoning Research'!AG11 -> 0 | L11: ='Zoning Research'!AH11 -> 0 | M11: ='Zoning Research'!AI11 -> AI Estimate | N11: 100 | O11: 100 | P11: =IF(J11="","",J11-AVERAGE(N11,O11)) -> 0
A12: Cicero | B12: IL | C12: 84000 | D12: A | E12: ='Zoning Research'!G12 -> 20 | F12: ='Zoning Research'!Q12 -> 20 | G12: ='Zoning Research'!V12 -> 20 | H12: ='Zoning Research'!Z12 -> 20 | I12: ='Zoning Research'!AE12 -> 20 | J12: ='Zoning Research'!AF12 -> 100 | K12: ='Zoning Research'!AG12 -> 0 | L12: ='Zoning Research'!AH12 -> 0 | M12: ='Zoning Research'!AI12 -> AI Estimate | N12: 100 | O12: 100 | P12: =IF(J12="","",J12-AVERAGE(N12,O12)) -> 0
A13: Bloomington | B13: IL | C13: 78000 | D13: A | E13: ='Zoning Research'!G13 -> 0 | F13: ='Zoning Research'!Q13 -> 0 | G13: ='Zoning Research'!V13 -> 0 | H13: ='Zoning Research'!Z13 -> 0 | I13: ='Zoning Research'!AE13 -> 0 | J13: ='Zoning Research'!AF13 -> 0 | K13: ='Zoning Research'!AG13 -> 0 | L13: ='Zoning Research'!AH13 -> 0 | M13: ='Zoning Research'!AI13 -> 0
A14: Arlington Heights | B14: IL | C14: 76000 | D14: A | E14: ='Zoning Research'!G14 -> 16 | F14: ='Zoning Research'!Q14 -> 16 | G14: ='Zoning Research'!V14 -> 16 | H14: ='Zoning Research'!Z14 -> 16 | I14: ='Zoning Research'!AE14 -> 16 | J14: ='Zoning Research'!AF14 -> 80 | K14: ='Zoning Research'!AG14 -> 0 | L14: ='Zoning Research'!AH14 -> 0 | M14: ='Zoning Research'!AI14 -> AI Estimate | N14: 75 | O14: 85 | P14: =IF(J14="","",J14-AVERAGE(N14,O14)) -> 0
A15: Evanston | B15: IL | C15: 74000 | D15: A | E15: ='Zoning Research'!G15 -> 16 | F15: ='Zoning Research'!Q15 -> 16 | G15: ='Zoning Research'!V15 -> 16 | H15: ='Zoning Research'!Z15 -> 16 | I15: ='Zoning Research'!AE15 -> 16 | J15: ='Zoning Research'!AF15 -> 80 | K15: ='Zoning Research'!AG15 -> 0 | L15: ='Zoning Research'!AH15 -> 0 | M15: ='Zoning Research'!AI15 -> AI Estimate | N15: 65 | O15: 100 | P15: =IF(J15="","",J15-AVERAGE(N15,O15)) -> -2.5
A16: Schaumburg | B16: IL | C16: 74000 | D16: A | E16: ='Zoning Research'!G16 -> 14 | F16: ='Zoning Research'!Q16 -> 14 | G16: ='Zoning Research'!V16 -> 14 | H16: ='Zoning Research'!Z16 -> 14 | I16: ='Zoning Research'!AE16 -> 14 | J16: ='Zoning Research'!AF16 -> 70 | K16: ='Zoning Research'!AG16 -> 0 | L16: ='Zoning Research'!AH16 -> 0 | M16: ='Zoning Research'!AI16 -> AI Estimate | N16: 75 | O16: 65 | P16: =IF(J16="","",J16-AVERAGE(N16,O16)) -> 0
A17: Bolingbrook | B17: IL | C17: 73000 | D17: A | E17: ='Zoning Research'!G17 -> 20 | F17: ='Zoning Research'!Q17 -> 20 | G17: ='Zoning Research'!V17 -> 20 | H17: ='Zoning Research'!Z17 -> 20 | I17: ='Zoning Research'!AE17 -> 20 | J17: ='Zoning Research'!AF17 -> 100 | K17: ='Zoning Research'!AG17 -> 0 | L17: ='Zoning Research'!AH17 -> 0 | M17: ='Zoning Research'!AI17 -> AI Estimate | N17: 100 | O17: 100 | P17: =IF(J17="","",J17-AVERAGE(N17,O17)) -> 0
A18: Decatur | B18: IL | C18: 70000 | D18: A | E18: ='Zoning Research'!G18 -> 0 | F18: ='Zoning Research'!Q18 -> 0 | G18: ='Zoning Research'!V18 -> 0 | H18: ='Zoning Research'!Z18 -> 0 | I18: ='Zoning Research'!AE18 -> 0 | J18: ='Zoning Research'!AF18 -> 0 | K18: ='Zoning Research'!AG18 -> 0 | L18: ='Zoning Research'!AH18 -> 0 | M18: ='Zoning Research'!AI18 -> 0
A19: Palatine | B19: IL | C19: 68000 | D19: A | E19: ='Zoning Research'!G19 -> 18 | F19: ='Zoning Research'!Q19 -> 18 | G19: ='Zoning Research'!V19 -> 18 | H19: ='Zoning Research'!Z19 -> 18 | I19: ='Zoning Research'!AE19 -> 18 | J19: ='Zoning Research'!AF19 -> 90 | K19: ='Zoning Research'!AG19 -> 0 | L19: ='Zoning Research'!AH19 -> 0 | M19: ='Zoning Research'!AI19 -> AI Estimate | N19: 75 | O19: 100 | P19: =IF(J19="","",J19-AVERAGE(N19,O19)) -> 2.5
A20: Skokie | B20: IL | C20: 65000 | D20: A | E20: ='Zoning Research'!G20 -> 18 | F20: ='Zoning Research'!Q20 -> 18 | G20: ='Zoning Research'!V20 -> 18 | H20: ='Zoning Research'!Z20 -> 18 | I20: ='Zoning Research'!AE20 -> 18 | J20: ='Zoning Research'!AF20 -> 90 | K20: ='Zoning Research'!AG20 -> 0 | L20: ='Zoning Research'!AH20 -> 0 | M20: ='Zoning Research'!AI20 -> AI Estimate | N20: 75 | O20: 100 | P20: =IF(J20="","",J20-AVERAGE(N20,O20)) -> 2.5
A21: Orland Park | B21: IL | C21: 58000 | D21: A | E21: ='Zoning Research'!G21 -> 18 | F21: ='Zoning Research'!Q21 -> 18 | G21: ='Zoning Research'!V21 -> 18 | H21: ='Zoning Research'!Z21 -> 18 | I21: ='Zoning Research'!AE21 -> 18 | J21: ='Zoning Research'!AF21 -> 90 | K21: ='Zoning Research'!AG21 -> 0 | L21: ='Zoning Research'!AH21 -> 0 | M21: ='Zoning Research'!AI21 -> AI Estimate | N21: 75 | O21: 100 | P21: =IF(J21="","",J21-AVERAGE(N21,O21)) -> 2.5
A22: Des Plaines | B22: IL | C22: 58000 | D22: A | E22: ='Zoning Research'!G22 -> 20 | F22: ='Zoning Research'!Q22 -> 20 | G22: ='Zoning Research'!V22 -> 20 | H22: ='Zoning Research'!Z22 -> 20 | I22: ='Zoning Research'!AE22 -> 20 | J22: ='Zoning Research'!AF22 -> 100 | K22: ='Zoning Research'!AG22 -> 0 | L22: ='Zoning Research'!AH22 -> 0 | M22: ='Zoning Research'!AI22 -> AI Estimate | N22: 100 | O22: 100 | P22: =IF(J22="","",J22-AVERAGE(N22,O22)) -> 0
A23: Tinley Park | B23: IL | C23: 57000 | D23: A | E23: ='Zoning Research'!G23 -> 20 | F23: ='Zoning Research'!Q23 -> 20 | G23: ='Zoning Research'!V23 -> 20 | H23: ='Zoning Research'!Z23 -> 20 | I23: ='Zoning Research'!AE23 -> 20 | J23: ='Zoning Research'!AF23 -> 100 | K23: ='Zoning Research'!AG23 -> 0 | L23: ='Zoning Research'!AH23 -> 0 | M23: ='Zoning Research'!AI23 -> AI Estimate | N23: 100 | O23: 100 | P23: =IF(J23="","",J23-AVERAGE(N23,O23)) -> 0
A24: Oak Lawn | B24: IL | C24: 57000 | D24: A | E24: ='Zoning Research'!G24 -> 0 | F24: ='Zoning Research'!Q24 -> 0 | G24: ='Zoning Research'!V24 -> 0 | H24: ='Zoning Research'!Z24 -> 0 | I24: ='Zoning Research'!AE24 -> 0 | J24: ='Zoning Research'!AF24 -> 0 | K24: ='Zoning Research'!AG24 -> 0 | L24: ='Zoning Research'!AH24 -> 0 | M24: ='Zoning Research'!AI24 -> 0
A25: Berwyn | B25: IL | C25: 55000 | D25: A | E25: ='Zoning Research'!G25 -> 20 | F25: ='Zoning Research'!Q25 -> 20 | G25: ='Zoning Research'!V25 -> 20 | H25: ='Zoning Research'!Z25 -> 20 | I25: ='Zoning Research'!AE25 -> 20 | J25: ='Zoning Research'!AF25 -> 100 | K25: ='Zoning Research'!AG25 -> 0 | L25: ='Zoning Research'!AH25 -> 0 | M25: ='Zoning Research'!AI25 -> AI Estimate | N25: 100 | O25: 100 | P25: =IF(J25="","",J25-AVERAGE(N25,O25)) -> 0
A26: Mount Prospect | B26: IL | C26: 54000 | D26: A | E26: ='Zoning Research'!G26 -> 18 | F26: ='Zoning Research'!Q26 -> 18 | G26: ='Zoning Research'!V26 -> 18 | H26: ='Zoning Research'!Z26 -> 18 | I26: ='Zoning Research'!AE26 -> 18 | J26: ='Zoning Research'!AF26 -> 90 | K26: ='Zoning Research'!AG26 -> 0 | L26: ='Zoning Research'!AH26 -> 0 | M26: ='Zoning Research'!AI26 -> AI Estimate | N26: 75 | O26: 100 | P26: =IF(J26="","",J26-AVERAGE(N26,O26)) -> 2.5
A27: Wheaton | B27: IL | C27: 53000 | D27: A | E27: ='Zoning Research'!G27 -> 18 | F27: ='Zoning Research'!Q27 -> 18 | G27: ='Zoning Research'!V27 -> 18 | H27: ='Zoning Research'!Z27 -> 18 | I27: ='Zoning Research'!AE27 -> 18 | J27: ='Zoning Research'!AF27 -> 90 | K27: ='Zoning Research'!AG27 -> 0 | L27: ='Zoning Research'!AH27 -> 0 | M27: ='Zoning Research'!AI27 -> AI Estimate | N27: 75 | O27: 100 | P27: =IF(J27="","",J27-AVERAGE(N27,O27)) -> 2.5
A28: Hoffman Estates | B28: IL | C28: 52000 | D28: A | E28: ='Zoning Research'!G28 -> 18 | F28: ='Zoning Research'!Q28 -> 18 | G28: ='Zoning Research'!V28 -> 18 | H28: ='Zoning Research'!Z28 -> 18 | I28: ='Zoning Research'!AE28 -> 18 | J28: ='Zoning Research'!AF28 -> 90 | K28: ='Zoning Research'!AG28 -> 0 | L28: ='Zoning Research'!AH28 -> 0 | M28: ='Zoning Research'!AI28 -> AI Estimate | N28: 75 | O28: 100 | P28: =IF(J28="","",J28-AVERAGE(N28,O28)) -> 2.5
A29: Oak Park | B29: IL | C29: 52000 | D29: A | E29: ='Zoning Research'!G29 -> 16 | F29: ='Zoning Research'!Q29 -> 16 | G29: ='Zoning Research'!V29 -> 16 | H29: ='Zoning Research'!Z29 -> 16 | I29: ='Zoning Research'!AE29 -> 16 | J29: ='Zoning Research'!AF29 -> 80 | K29: ='Zoning Research'!AG29 -> 0 | L29: ='Zoning Research'!AH29 -> 0 | M29: ='Zoning Research'!AI29 -> AI Estimate | N29: 65 | O29: 100 | P29: =IF(J29="","",J29-AVERAGE(N29,O29)) -> -2.5
A30: Normal | B30: IL | C30: 52000 | D30: A | E30: ='Zoning Research'!G30 -> 0 | F30: ='Zoning Research'!Q30 -> 0 | G30: ='Zoning Research'!V30 -> 0 | H30: ='Zoning Research'!Z30 -> 0 | I30: ='Zoning Research'!AE30 -> 0 | J30: ='Zoning Research'!AF30 -> 0 | K30: ='Zoning Research'!AG30 -> 0 | L30: ='Zoning Research'!AH30 -> 0 | M30: ='Zoning Research'!AI30 -> 0
A31: Downers Grove | B31: IL | C31: 49000 | D31: A | E31: ='Zoning Research'!G31 -> 16 | F31: ='Zoning Research'!Q31 -> 16 | G31: ='Zoning Research'!V31 -> 16 | H31: ='Zoning Research'!Z31 -> 16 | I31: ='Zoning Research'!AE31 -> 16 | J31: ='Zoning Research'!AF31 -> 80 | K31: ='Zoning Research'!AG31 -> 0 | L31: ='Zoning Research'!AH31 -> 0 | M31: ='Zoning Research'!AI31 -> AI Estimate | N31: 75 | O31: 85 | P31: =IF(J31="","",J31-AVERAGE(N31,O31)) -> 0
A32: Glenview | B32: IL | C32: 47000 | D32: A | E32: ='Zoning Research'!G32 -> 18 | F32: ='Zoning Research'!Q32 -> 18 | G32: ='Zoning Research'!V32 -> 18 | H32: ='Zoning Research'!Z32 -> 18 | I32: ='Zoning Research'!AE32 -> 18 | J32: ='Zoning Research'!AF32 -> 90 | K32: ='Zoning Research'!AG32 -> 0 | L32: ='Zoning Research'!AH32 -> 0 | M32: ='Zoning Research'!AI32 -> AI Estimate | N32: 75 | O32: 100 | P32: =IF(J32="","",J32-AVERAGE(N32,O32)) -> 2.5
A33: Elmhurst | B33: IL | C33: 46000 | D33: A | E33: ='Zoning Research'!G33 -> 18 | F33: ='Zoning Research'!Q33 -> 18 | G33: ='Zoning Research'!V33 -> 18 | H33: ='Zoning Research'!Z33 -> 18 | I33: ='Zoning Research'!AE33 -> 18 | J33: ='Zoning Research'!AF33 -> 90 | K33: ='Zoning Research'!AG33 -> 0 | L33: ='Zoning Research'!AH33 -> 0 | M33: ='Zoning Research'!AI33 -> AI Estimate | N33: 75 | O33: 100 | P33: =IF(J33="","",J33-AVERAGE(N33,O33)) -> 2.5
A34: Lombard | B34: IL | C34: 44000 | D34: A | E34: ='Zoning Research'!G34 -> 18 | F34: ='Zoning Research'!Q34 -> 18 | G34: ='Zoning Research'!V34 -> 18 | H34: ='Zoning Research'!Z34 -> 18 | I34: ='Zoning Research'!AE34 -> 18 | J34: ='Zoning Research'!AF34 -> 90 | K34: ='Zoning Research'!AG34 -> 0 | L34: ='Zoning Research'!AH34 -> 0 | M34: ='Zoning Research'!AI34 -> AI Estimate | N34: 75 | O34: 100 | P34: =IF(J34="","",J34-AVERAGE(N34,O34)) -> 2.5
A35: DeKalb | B35: IL | C35: 44000 | D35: A | E35: ='Zoning Research'!G35 -> 0 | F35: ='Zoning Research'!Q35 -> 0 | G35: ='Zoning Research'!V35 -> 0 | H35: ='Zoning Research'!Z35 -> 0 | I35: ='Zoning Research'!AE35 -> 0 | J35: ='Zoning Research'!AF35 -> 0 | K35: ='Zoning Research'!AG35 -> 0 | L35: ='Zoning Research'!AH35 -> 0 | M35: ='Zoning Research'!AI35 -> 0
A36: Moline | B36: IL | C36: 42000 | D36: A | E36: ='Zoning Research'!G36 -> 0 | F36: ='Zoning Research'!Q36 -> 0 | G36: ='Zoning Research'!V36 -> 0 | H36: ='Zoning Research'!Z36 -> 0 | I36: ='Zoning Research'!AE36 -> 0 | J36: ='Zoning Research'!AF36 -> 0 | K36: ='Zoning Research'!AG36 -> 0 | L36: ='Zoning Research'!AH36 -> 0 | M36: ='Zoning Research'!AI36 -> 0
A37: Belleville | B37: IL | C37: 42000 | D37: A | E37: ='Zoning Research'!G37 -> 0 | F37: ='Zoning Research'!Q37 -> 0 | G37: ='Zoning Research'!V37 -> 0 | H37: ='Zoning Research'!Z37 -> 0 | I37: ='Zoning Research'!AE37 -> 0 | J37: ='Zoning Research'!AF37 -> 0 | K37: ='Zoning Research'!AG37 -> 0 | L37: ='Zoning Research'!AH37 -> 0 | M37: ='Zoning Research'!AI37 -> 0
A38: Plainfield | B38: IL | C38: 41000 | D38: A | E38: ='Zoning Research'!G38 -> 20 | F38: ='Zoning Research'!Q38 -> 20 | G38: ='Zoning Research'!V38 -> 20 | H38: ='Zoning Research'!Z38 -> 20 | I38: ='Zoning Research'!AE38 -> 20 | J38: ='Zoning Research'!AF38 -> 100 | K38: ='Zoning Research'!AG38 -> 0 | L38: ='Zoning Research'!AH38 -> 0 | M38: ='Zoning Research'!AI38 -> AI Estimate | N38: 100 | O38: 100 | P38: =IF(J38="","",J38-AVERAGE(N38,O38)) -> 0
A39: Bartlett | B39: IL | C39: 41000 | D39: A | E39: ='Zoning Research'!G39 -> 0 | F39: ='Zoning Research'!Q39 -> 0 | G39: ='Zoning Research'!V39 -> 0 | H39: ='Zoning Research'!Z39 -> 0 | I39: ='Zoning Research'!AE39 -> 0 | J39: ='Zoning Research'!AF39 -> 0 | K39: ='Zoning Research'!AG39 -> 0 | L39: ='Zoning Research'!AH39 -> 0 | M39: ='Zoning Research'!AI39 -> 0
A40: Buffalo Grove | B40: IL | C40: 41000 | D40: A | E40: ='Zoning Research'!G40 -> 0 | F40: ='Zoning Research'!Q40 -> 0 | G40: ='Zoning Research'!V40 -> 0 | H40: ='Zoning Research'!Z40 -> 0 | I40: ='Zoning Research'!AE40 -> 0 | J40: ='Zoning Research'!AF40 -> 0 | K40: ='Zoning Research'!AG40 -> 0 | L40: ='Zoning Research'!AH40 -> 0 | M40: ='Zoning Research'!AI40 -> 0
A41: Carol Stream | B41: IL | C41: 40000 | D41: A | E41: ='Zoning Research'!G41 -> 20 | F41: ='Zoning Research'!Q41 -> 20 | G41: ='Zoning Research'!V41 -> 20 | H41: ='Zoning Research'!Z41 -> 20 | I41: ='Zoning Research'!AE41 -> 20 | J41: ='Zoning Research'!AF41 -> 100 | K41: ='Zoning Research'!AG41 -> 0 | L41: ='Zoning Research'!AH41 -> 0 | M41: ='Zoning Research'!AI41 -> AI Estimate | N41: 100 | O41: 100 | P41: =IF(J41="","",J41-AVERAGE(N41,O41)) -> 0
A42: Streamwood | B42: IL | C42: 40000 | D42: A | E42: ='Zoning Research'!G42 -> 0 | F42: ='Zoning Research'!Q42 -> 0 | G42: ='Zoning Research'!V42 -> 0 | H42: ='Zoning Research'!Z42 -> 0 | I42: ='Zoning Research'!AE42 -> 0 | J42: ='Zoning Research'!AF42 -> 0 | K42: ='Zoning Research'!AG42 -> 0 | L42: ='Zoning Research'!AH42 -> 0 | M42: ='Zoning Research'!AI42 -> 0
A43: Quincy | B43: IL | C43: 40000 | D43: A | E43: ='Zoning Research'!G43 -> 0 | F43: ='Zoning Research'!Q43 -> 0 | G43: ='Zoning Research'!V43 -> 0 | H43: ='Zoning Research'!Z43 -> 0 | I43: ='Zoning Research'!AE43 -> 0 | J43: ='Zoning Research'!AF43 -> 0 | K43: ='Zoning Research'!AG43 -> 0 | L43: ='Zoning Research'!AH43 -> 0 | M43: ='Zoning Research'!AI43 -> 0
A44: Romeoville | B44: IL | C44: 39000 | D44: A | E44: ='Zoning Research'!G44 -> 20 | F44: ='Zoning Research'!Q44 -> 20 | G44: ='Zoning Research'!V44 -> 20 | H44: ='Zoning Research'!Z44 -> 20 | I44: ='Zoning Research'!AE44 -> 20 | J44: ='Zoning Research'!AF44 -> 100 | K44: ='Zoning Research'!AG44 -> 0 | L44: ='Zoning Research'!AH44 -> 0 | M44: ='Zoning Research'!AI44 -> AI Estimate | N44: 100 | O44: 100 | P44: =IF(J44="","",J44-AVERAGE(N44,O44)) -> 0
A45: Crystal Lake | B45: IL | C45: 39000 | D45: A | E45: ='Zoning Research'!G45 -> 0 | F45: ='Zoning Research'!Q45 -> 0 | G45: ='Zoning Research'!V45 -> 0 | H45: ='Zoning Research'!Z45 -> 0 | I45: ='Zoning Research'!AE45 -> 0 | J45: ='Zoning Research'!AF45 -> 0 | K45: ='Zoning Research'!AG45 -> 0 | L45: ='Zoning Research'!AH45 -> 0 | M45: ='Zoning Research'!AI45 -> 0
A46: Wheeling | B46: IL | C46: 38000 | D46: A | E46: ='Zoning Research'!G46 -> 0 | F46: ='Zoning Research'!Q46 -> 0 | G46: ='Zoning Research'!V46 -> 0 | H46: ='Zoning Research'!Z46 -> 0 | I46: ='Zoning Research'!AE46 -> 0 | J46: ='Zoning Research'!AF46 -> 0 | K46: ='Zoning Research'!AG46 -> 0 | L46: ='Zoning Research'!AH46 -> 0 | M46: ='Zoning Research'!AI46 -> 0
A47: Urbana | B47: IL | C47: 38000 | D47: A | E47: ='Zoning Research'!G47 -> 0 | F47: ='Zoning Research'!Q47 -> 0 | G47: ='Zoning Research'!V47 -> 0 | H47: ='Zoning Research'!Z47 -> 0 | I47: ='Zoning Research'!AE47 -> 0 | J47: ='Zoning Research'!AF47 -> 0 | K47: ='Zoning Research'!AG47 -> 0 | L47: ='Zoning Research'!AH47 -> 0 | M47: ='Zoning Research'!AI47 -> 0
A48: Park Ridge | B48: IL | C48: 37000 | D48: A | E48: ='Zoning Research'!G48 -> 16 | F48: ='Zoning Research'!Q48 -> 16 | G48: ='Zoning Research'!V48 -> 16 | H48: ='Zoning Research'!Z48 -> 16 | I48: ='Zoning Research'!AE48 -> 16 | J48: ='Zoning Research'!AF48 -> 80 | K48: ='Zoning Research'!AG48 -> 0 | L48: ='Zoning Research'!AH48 -> 0 | M48: ='Zoning Research'!AI48 -> AI Estimate | N48: 65 | O48: 100 | P48: =IF(J48="","",J48-AVERAGE(N48,O48)) -> -2.5
A49: Hanover Park | B49: IL | C49: 37000 | D49: A | E49: ='Zoning Research'!G49 -> 0 | F49: ='Zoning Research'!Q49 -> 0 | G49: ='Zoning Research'!V49 -> 0 | H49: ='Zoning Research'!Z49 -> 0 | I49: ='Zoning Research'!AE49 -> 0 | J49: ='Zoning Research'!AF49 -> 0 | K49: ='Zoning Research'!AG49 -> 0 | L49: ='Zoning Research'!AH49 -> 0 | M49: ='Zoning Research'!AI49 -> 0
A50: Carpentersville | B50: IL | C50: 37000 | D50: A | E50: ='Zoning Research'!G50 -> 0 | F50: ='Zoning Research'!Q50 -> 0 | G50: ='Zoning Research'!V50 -> 0 | H50: ='Zoning Research'!Z50 -> 0 | I50: ='Zoning Research'!AE50 -> 0 | J50: ='Zoning Research'!AF50 -> 0 | K50: ='Zoning Research'!AG50 -> 0 | L50: ='Zoning Research'!AH50 -> 0 | M50: ='Zoning Research'!AI50 -> 0
A51: Oswego | B51: IL | C51: 37000 | D51: A | E51: ='Zoning Research'!G51 -> 0 | F51: ='Zoning Research'!Q51 -> 0 | G51: ='Zoning Research'!V51 -> 0 | H51: ='Zoning Research'!Z51 -> 0 | I51: ='Zoning Research'!AE51 -> 0 | J51: ='Zoning Research'!AF51 -> 0 | K51: ='Zoning Research'!AG51 -> 0 | L51: ='Zoning Research'!AH51 -> 0 | M51: ='Zoning Research'!AI51 -> 0
A52: Rock Island | B52: IL | C52: 37000 | D52: A | E52: ='Zoning Research'!G52 -> 0 | F52: ='Zoning Research'!Q52 -> 0 | G52: ='Zoning Research'!V52 -> 0 | H52: ='Zoning Research'!Z52 -> 0 | I52: ='Zoning Research'!AE52 -> 0 | J52: ='Zoning Research'!AF52 -> 0 | K52: ='Zoning Research'!AG52 -> 0 | L52: ='Zoning Research'!AH52 -> 0 | M52: ='Zoning Research'!AI52 -> 0
A53: Addison | B53: IL | C53: 36000 | D53: A | E53: ='Zoning Research'!G53 -> 20 | F53: ='Zoning Research'!Q53 -> 20 | G53: ='Zoning Research'!V53 -> 20 | H53: ='Zoning Research'!Z53 -> 20 | I53: ='Zoning Research'!AE53 -> 20 | J53: ='Zoning Research'!AF53 -> 100 | K53: ='Zoning Research'!AG53 -> 0 | L53: ='Zoning Research'!AH53 -> 0 | M53: ='Zoning Research'!AI53 -> AI Estimate | N53: 100 | O53: 100 | P53: =IF(J53="","",J53-AVERAGE(N53,O53)) -> 0
A54: Calumet City | B54: IL | C54: 36000 | D54: A | E54: ='Zoning Research'!G54 -> 0 | F54: ='Zoning Research'!Q54 -> 0 | G54: ='Zoning Research'!V54 -> 0 | H54: ='Zoning Research'!Z54 -> 0 | I54: ='Zoning Research'!AE54 -> 0 | J54: ='Zoning Research'!AF54 -> 0 | K54: ='Zoning Research'!AG54 -> 0 | L54: ='Zoning Research'!AH54 -> 0 | M54: ='Zoning Research'!AI54 -> 0
A55: Glendale Heights | B55: IL | C55: 34000 | D55: A | E55: ='Zoning Research'!G55 -> 20 | F55: ='Zoning Research'!Q55 -> 20 | G55: ='Zoning Research'!V55 -> 20 | H55: ='Zoning Research'!Z55 -> 20 | I55: ='Zoning Research'!AE55 -> 20 | J55: ='Zoning Research'!AF55 -> 100 | K55: ='Zoning Research'!AG55 -> 0 | L55: ='Zoning Research'!AH55 -> 0 | M55: ='Zoning Research'!AI55 -> AI Estimate | N55: 100 | O55: 100 | P55: =IF(J55="","",J55-AVERAGE(N55,O55)) -> 0
A56: Northbrook | B56: IL | C56: 33000 | D56: A | E56: ='Zoning Research'!G56 -> 18 | F56: ='Zoning Research'!Q56 -> 18 | G56: ='Zoning Research'!V56 -> 18 | H56: ='Zoning Research'!Z56 -> 18 | I56: ='Zoning Research'!AE56 -> 18 | J56: ='Zoning Research'!AF56 -> 90 | K56: ='Zoning Research'!AG56 -> 0 | L56: ='Zoning Research'!AH56 -> 0 | M56: ='Zoning Research'!AI56 -> AI Estimate | N56: 75 | O56: 100 | P56: =IF(J56="","",J56-AVERAGE(N56,O56)) -> 2.5
A57: St. Charles | B57: IL | C57: 33000 | D57: A | E57: ='Zoning Research'!G57 -> 0 | F57: ='Zoning Research'!Q57 -> 0 | G57: ='Zoning Research'!V57 -> 0 | H57: ='Zoning Research'!Z57 -> 0 | I57: ='Zoning Research'!AE57 -> 0 | J57: ='Zoning Research'!AF57 -> 0 | K57: ='Zoning Research'!AG57 -> 0 | L57: ='Zoning Research'!AH57 -> 0 | M57: ='Zoning Research'!AI57 -> 0
A58: Woodridge | B58: IL | C58: 33000 | D58: A | E58: ='Zoning Research'!G58 -> 0 | F58: ='Zoning Research'!Q58 -> 0 | G58: ='Zoning Research'!V58 -> 0 | H58: ='Zoning Research'!Z58 -> 0 | I58: ='Zoning Research'!AE58 -> 0 | J58: ='Zoning Research'!AF58 -> 0 | K58: ='Zoning Research'!AG58 -> 0 | L58: ='Zoning Research'!AH58 -> 0 | M58: ='Zoning Research'!AI58 -> 0
A59: Pekin | B59: IL | C59: 33000 | D59: A | E59: ='Zoning Research'!G59 -> 0 | F59: ='Zoning Research'!Q59 -> 0 | G59: ='Zoning Research'!V59 -> 0 | H59: ='Zoning Research'!Z59 -> 0 | I59: ='Zoning Research'!AE59 -> 0 | J59: ='Zoning Research'!AF59 -> 0 | K59: ='Zoning Research'!AG59 -> 0 | L59: ='Zoning Research'!AH59 -> 0 | M59: ='Zoning Research'!AI59 -> 0
A60: Elk Grove Village | B60: IL | C60: 32000 | D60: A | E60: ='Zoning Research'!G60 -> 20 | F60: ='Zoning Research'!Q60 -> 20 | G60: ='Zoning Research'!V60 -> 20 | H60: ='Zoning Research'!Z60 -> 20 | I60: ='Zoning Research'!AE60 -> 20 | J60: ='Zoning Research'!AF60 -> 100 | K60: ='Zoning Research'!AG60 -> 0 | L60: ='Zoning Research'!AH60 -> 0 | M60: ='Zoning Research'!AI60 -> AI Estimate | N60: 100 | O60: 100 | P60: =IF(J60="","",J60-AVERAGE(N60,O60)) -> 0
A61: Mundelein | B61: IL | C61: 31000 | D61: A | E61: ='Zoning Research'!G61 -> 20 | F61: ='Zoning Research'!Q61 -> 20 | G61: ='Zoning Research'!V61 -> 20 | H61: ='Zoning Research'!Z61 -> 20 | I61: ='Zoning Research'!AE61 -> 20 | J61: ='Zoning Research'!AF61 -> 100 | K61: ='Zoning Research'!AG61 -> 0 | L61: ='Zoning Research'!AH61 -> 0 | M61: ='Zoning Research'!AI61 -> AI Estimate | N61: 100 | O61: 100 | P61: =IF(J61="","",J61-AVERAGE(N61,O61)) -> 0
A62: Gurnee | B62: IL | C62: 31000 | D62: A | E62: ='Zoning Research'!G62 -> 0 | F62: ='Zoning Research'!Q62 -> 0 | G62: ='Zoning Research'!V62 -> 0 | H62: ='Zoning Research'!Z62 -> 0 | I62: ='Zoning Research'!AE62 -> 0 | J62: ='Zoning Research'!AF62 -> 0 | K62: ='Zoning Research'!AG62 -> 0 | L62: ='Zoning Research'!AH62 -> 0 | M62: ='Zoning Research'!AI62 -> 0
A63: Lake in the Hills | B63: IL | C63: 30000 | D63: A | E63: ='Zoning Research'!G63 -> 0 | F63: ='Zoning Research'!Q63 -> 0 | G63: ='Zoning Research'!V63 -> 0 | H63: ='Zoning Research'!Z63 -> 0 | I63: ='Zoning Research'!AE63 -> 0 | J63: ='Zoning Research'!AF63 -> 0 | K63: ='Zoning Research'!AG63 -> 0 | L63: ='Zoning Research'!AH63 -> 0 | M63: ='Zoning Research'!AI63 -> 0
A64: Highland Park | B64: IL | C64: 30000 | D64: A | E64: ='Zoning Research'!G64 -> 16 | F64: ='Zoning Research'!Q64 -> 16 | G64: ='Zoning Research'!V64 -> 16 | H64: ='Zoning Research'!Z64 -> 16 | I64: ='Zoning Research'!AE64 -> 16 | J64: ='Zoning Research'!AF64 -> 80 | K64: ='Zoning Research'!AG64 -> 0 | L64: ='Zoning Research'!AH64 -> 0 | M64: ='Zoning Research'!AI64 -> AI Estimate | N64: 65 | O64: 100 | P64: =IF(J64="","",J64-AVERAGE(N64,O64)) -> -2.5
A65: Niles | B65: IL | C65: 30000 | D65: A | E65: ='Zoning Research'!G65 -> 0 | F65: ='Zoning Research'!Q65 -> 0 | G65: ='Zoning Research'!V65 -> 0 | H65: ='Zoning Research'!Z65 -> 0 | I65: ='Zoning Research'!AE65 -> 0 | J65: ='Zoning Research'!AF65 -> 0 | K65: ='Zoning Research'!AG65 -> 0 | L65: ='Zoning Research'!AH65 -> 0 | M65: ='Zoning Research'!AI65 -> 0
A66: Algonquin | B66: IL | C66: 30000 | D66: A | E66: ='Zoning Research'!G66 -> 0 | F66: ='Zoning Research'!Q66 -> 0 | G66: ='Zoning Research'!V66 -> 0 | H66: ='Zoning Research'!Z66 -> 0 | I66: ='Zoning Research'!AE66 -> 0 | J66: ='Zoning Research'!AF66 -> 0 | K66: ='Zoning Research'!AG66 -> 0 | L66: ='Zoning Research'!AH66 -> 0 | M66: ='Zoning Research'!AI66 -> 0
A67: Danville | B67: IL | C67: 30000 | D67: A | E67: ='Zoning Research'!G67 -> 0 | F67: ='Zoning Research'!Q67 -> 0 | G67: ='Zoning Research'!V67 -> 0 | H67: ='Zoning Research'!Z67 -> 0 | I67: ='Zoning Research'!AE67 -> 0 | J67: ='Zoning Research'!AF67 -> 0 | K67: ='Zoning Research'!AG67 -> 0 | L67: ='Zoning Research'!AH67 -> 0 | M67: ='Zoning Research'!AI67 -> 0
A68: Galesburg | B68: IL | C68: 30000 | D68: A | E68: ='Zoning Research'!G68 -> 0 | F68: ='Zoning Research'!Q68 -> 0 | G68: ='Zoning Research'!V68 -> 0 | H68: ='Zoning Research'!Z68 -> 0 | I68: ='Zoning Research'!AE68 -> 0 | J68: ='Zoning Research'!AF68 -> 0 | K68: ='Zoning Research'!AG68 -> 0 | L68: ='Zoning Research'!AH68 -> 0 | M68: ='Zoning Research'!AI68 -> 0
A69: O'Fallon | B69: IL | C69: 30000 | D69: A | E69: ='Zoning Research'!G69 -> 0 | F69: ='Zoning Research'!Q69 -> 0 | G69: ='Zoning Research'!V69 -> 0 | H69: ='Zoning Research'!Z69 -> 0 | I69: ='Zoning Research'!AE69 -> 0 | J69: ='Zoning Research'!AF69 -> 0 | K69: ='Zoning Research'!AG69 -> 0 | L69: ='Zoning Research'!AH69 -> 0 | M69: ='Zoning Research'!AI69 -> 0
A70: Wilmette | B70: IL | C70: 28000 | D70: A | E70: ='Zoning Research'!G70 -> 16 | F70: ='Zoning Research'!Q70 -> 16 | G70: ='Zoning Research'!V70 -> 16 | H70: ='Zoning Research'!Z70 -> 16 | I70: ='Zoning Research'!AE70 -> 16 | J70: ='Zoning Research'!AF70 -> 80 | K70: ='Zoning Research'!AG70 -> 0 | L70: ='Zoning Research'!AH70 -> 0 | M70: ='Zoning Research'!AI70 -> AI Estimate | N70: 65 | O70: 100 | P70: =IF(J70="","",J70-AVERAGE(N70,O70)) -> -2.5
A71: Oak Forest | B71: IL | C71: 28000 | D71: A | E71: ='Zoning Research'!G71 -> 20 | F71: ='Zoning Research'!Q71 -> 20 | G71: ='Zoning Research'!V71 -> 20 | H71: ='Zoning Research'!Z71 -> 20 | I71: ='Zoning Research'!AE71 -> 20 | J71: ='Zoning Research'!AF71 -> 100 | K71: ='Zoning Research'!AG71 -> 0 | L71: ='Zoning Research'!AH71 -> 0 | M71: ='Zoning Research'!AI71 -> AI Estimate | N71: 100 | O71: 100 | P71: =IF(J71="","",J71-AVERAGE(N71,O71)) -> 0
A72: Granite City | B72: IL | C72: 28000 | D72: A | E72: ='Zoning Research'!G72 -> 0 | F72: ='Zoning Research'!Q72 -> 0 | G72: ='Zoning Research'!V72 -> 0 | H72: ='Zoning Research'!Z72 -> 0 | I72: ='Zoning Research'!AE72 -> 0 | J72: ='Zoning Research'!AF72 -> 0 | K72: ='Zoning Research'!AG72 -> 0 | L72: ='Zoning Research'!AH72 -> 0 | M72: ='Zoning Research'!AI72 -> 0
A73: Huntley | B73: IL | C73: 27000 | D73: A | E73: ='Zoning Research'!G73 -> 0 | F73: ='Zoning Research'!Q73 -> 0 | G73: ='Zoning Research'!V73 -> 0 | H73: ='Zoning Research'!Z73 -> 0 | I73: ='Zoning Research'!AE73 -> 0 | J73: ='Zoning Research'!AF73 -> 0 | K73: ='Zoning Research'!AG73 -> 0 | L73: ='Zoning Research'!AH73 -> 0 | M73: ='Zoning Research'!AI73 -> 0
A74: McHenry | B74: IL | C74: 27000 | D74: A | E74: ='Zoning Research'!G74 -> 0 | F74: ='Zoning Research'!Q74 -> 0 | G74: ='Zoning Research'!V74 -> 0 | H74: ='Zoning Research'!Z74 -> 0 | I74: ='Zoning Research'!AE74 -> 0 | J74: ='Zoning Research'!AF74 -> 0 | K74: ='Zoning Research'!AG74 -> 0 | L74: ='Zoning Research'!AH74 -> 0 | M74: ='Zoning Research'!AI74 -> 0
A75: New Lenox | B75: IL | C75: 27000 | D75: A | E75: ='Zoning Research'!G75 -> 0 | F75: ='Zoning Research'!Q75 -> 0 | G75: ='Zoning Research'!V75 -> 0 | H75: ='Zoning Research'!Z75 -> 0 | I75: ='Zoning Research'!AE75 -> 0 | J75: ='Zoning Research'!AF75 -> 0 | K75: ='Zoning Research'!AG75 -> 0 | L75: ='Zoning Research'!AH75 -> 0 | M75: ='Zoning Research'!AI75 -> 0
A76: Batavia | B76: IL | C76: 26000 | D76: A | E76: ='Zoning Research'!G76 -> 0 | F76: ='Zoning Research'!Q76 -> 0 | G76: ='Zoning Research'!V76 -> 0 | H76: ='Zoning Research'!Z76 -> 0 | I76: ='Zoning Research'!AE76 -> 0 | J76: ='Zoning Research'!AF76 -> 0 | K76: ='Zoning Research'!AG76 -> 0 | L76: ='Zoning Research'!AH76 -> 0 | M76: ='Zoning Research'!AI76 -> 0
A77: Vernon Hills | B77: IL | C77: 26000 | D77: A | E77: ='Zoning Research'!G77 -> 0 | F77: ='Zoning Research'!Q77 -> 0 | G77: ='Zoning Research'!V77 -> 0 | H77: ='Zoning Research'!Z77 -> 0 | I77: ='Zoning Research'!AE77 -> 0 | J77: ='Zoning Research'!AF77 -> 0 | K77: ='Zoning Research'!AG77 -> 0 | L77: ='Zoning Research'!AH77 -> 0 | M77: ='Zoning Research'!AI77 -> 0
A78: Alton | B78: IL | C78: 26000 | D78: A | E78: ='Zoning Research'!G78 -> 0 | F78: ='Zoning Research'!Q78 -> 0 | G78: ='Zoning Research'!V78 -> 0 | H78: ='Zoning Research'!Z78 -> 0 | I78: ='Zoning Research'!AE78 -> 0 | J78: ='Zoning Research'!AF78 -> 0 | K78: ='Zoning Research'!AG78 -> 0 | L78: ='Zoning Research'!AH78 -> 0 | M78: ='Zoning Research'!AI78 -> 0
A79: Lockport | B79: IL | C79: 25000 | D79: A | E79: ='Zoning Research'!G79 -> 20 | F79: ='Zoning Research'!Q79 -> 20 | G79: ='Zoning Research'!V79 -> 20 | H79: ='Zoning Research'!Z79 -> 20 | I79: ='Zoning Research'!AE79 -> 20 | J79: ='Zoning Research'!AF79 -> 100 | K79: ='Zoning Research'!AG79 -> 0 | L79: ='Zoning Research'!AH79 -> 0 | M79: ='Zoning Research'!AI79 -> AI Estimate | N79: 100 | O79: 100 | P79: =IF(J79="","",J79-AVERAGE(N79,O79)) -> 0
A80: Woodstock | B80: IL | C80: 25000 | D80: A | E80: ='Zoning Research'!G80 -> 0 | F80: ='Zoning Research'!Q80 -> 0 | G80: ='Zoning Research'!V80 -> 0 | H80: ='Zoning Research'!Z80 -> 0 | I80: ='Zoning Research'!AE80 -> 0 | J80: ='Zoning Research'!AF80 -> 0 | K80: ='Zoning Research'!AG80 -> 0 | L80: ='Zoning Research'!AH80 -> 0 | M80: ='Zoning Research'!AI80 -> 0
A81: Collinsville | B81: IL | C81: 25000 | D81: A | E81: ='Zoning Research'!G81 -> 0 | F81: ='Zoning Research'!Q81 -> 0 | G81: ='Zoning Research'!V81 -> 0 | H81: ='Zoning Research'!Z81 -> 0 | I81: ='Zoning Research'!AE81 -> 0 | J81: ='Zoning Research'!AF81 -> 0 | K81: ='Zoning Research'!AG81 -> 0 | L81: ='Zoning Research'!AH81 -> 0 | M81: ='Zoning Research'!AI81 -> 0
A82: Edwardsville | B82: IL | C82: 25000 | D82: A | E82: ='Zoning Research'!G82 -> 0 | F82: ='Zoning Research'!Q82 -> 0 | G82: ='Zoning Research'!V82 -> 0 | H82: ='Zoning Research'!Z82 -> 0 | I82: ='Zoning Research'!AE82 -> 0 | J82: ='Zoning Research'!AF82 -> 0 | K82: ='Zoning Research'!AG82 -> 0 | L82: ='Zoning Research'!AH82 -> 0 | M82: ='Zoning Research'!AI82 -> 0
A83: Westmont | B83: IL | C83: 24000 | D83: A | E83: ='Zoning Research'!G83 -> 16 | F83: ='Zoning Research'!Q83 -> 16 | G83: ='Zoning Research'!V83 -> 16 | H83: ='Zoning Research'!Z83 -> 16 | I83: ='Zoning Research'!AE83 -> 16 | J83: ='Zoning Research'!AF83 -> 80 | K83: ='Zoning Research'!AG83 -> 0 | L83: ='Zoning Research'!AH83 -> 0 | M83: ='Zoning Research'!AI83 -> AI Estimate | N83: 65 | O83: 100 | P83: =IF(J83="","",J83-AVERAGE(N83,O83)) -> -2.5
A84: Maywood | B84: IL | C84: 24000 | D84: A | E84: ='Zoning Research'!G84 -> 0 | F84: ='Zoning Research'!Q84 -> 0 | G84: ='Zoning Research'!V84 -> 0 | H84: ='Zoning Research'!Z84 -> 0 | I84: ='Zoning Research'!AE84 -> 0 | J84: ='Zoning Research'!AF84 -> 0 | K84: ='Zoning Research'!AG84 -> 0 | L84: ='Zoning Research'!AH84 -> 0 | M84: ='Zoning Research'!AI84 -> 0
A85: Rolling Meadows | B85: IL | C85: 24000 | D85: A | E85: ='Zoning Research'!G85 -> 18 | F85: ='Zoning Research'!Q85 -> 18 | G85: ='Zoning Research'!V85 -> 18 | H85: ='Zoning Research'!Z85 -> 18 | I85: ='Zoning Research'!AE85 -> 18 | J85: ='Zoning Research'!AF85 -> 90 | K85: ='Zoning Research'!AG85 -> 0 | L85: ='Zoning Research'!AH85 -> 0 | M85: ='Zoning Research'!AI85 -> AI Estimate | N85: 75 | O85: 100 | P85: =IF(J85="","",J85-AVERAGE(N85,O85)) -> 2.5
A86: Morton Grove | B86: IL | C86: 23000 | D86: A | E86: ='Zoning Research'!G86 -> 0 | F86: ='Zoning Research'!Q86 -> 0 | G86: ='Zoning Research'!V86 -> 0 | H86: ='Zoning Research'!Z86 -> 0 | I86: ='Zoning Research'!AE86 -> 0 | J86: ='Zoning Research'!AF86 -> 0 | K86: ='Zoning Research'!AG86 -> 0 | L86: ='Zoning Research'!AH86 -> 0 | M86: ='Zoning Research'!AI86 -> 0
A87: Lisle | B87: IL | C87: 23000 | D87: A | E87: ='Zoning Research'!G87 -> 0 | F87: ='Zoning Research'!Q87 -> 0 | G87: ='Zoning Research'!V87 -> 0 | H87: ='Zoning Research'!Z87 -> 0 | I87: ='Zoning Research'!AE87 -> 0 | J87: ='Zoning Research'!AF87 -> 0 | K87: ='Zoning Research'!AG87 -> 0 | L87: ='Zoning Research'!AH87 -> 0 | M87: ='Zoning Research'!AI87 -> 0
A88: Roselle | B88: IL | C88: 23000 | D88: A | E88: ='Zoning Research'!G88 -> 0 | F88: ='Zoning Research'!Q88 -> 0 | G88: ='Zoning Research'!V88 -> 0 | H88: ='Zoning Research'!Z88 -> 0 | I88: ='Zoning Research'!AE88 -> 0 | J88: ='Zoning Research'!AF88 -> 0 | K88: ='Zoning Research'!AG88 -> 0 | L88: ='Zoning Research'!AH88 -> 0 | M88: ='Zoning Research'!AI88 -> 0
A89: Blue Island | B89: IL | C89: 23000 | D89: A | E89: ='Zoning Research'!G89 -> 20 | F89: ='Zoning Research'!Q89 -> 20 | G89: ='Zoning Research'!V89 -> 20 | H89: ='Zoning Research'!Z89 -> 20 | I89: ='Zoning Research'!AE89 -> 20 | J89: ='Zoning Research'!AF89 -> 100 | K89: ='Zoning Research'!AG89 -> 0 | L89: ='Zoning Research'!AH89 -> 0 | M89: ='Zoning Research'!AI89 -> AI Estimate | N89: 100 | O89: 100 | P89: =IF(J89="","",J89-AVERAGE(N89,O89)) -> 0
A90: Melrose Park | B90: IL | C90: 23000 | D90: A | E90: ='Zoning Research'!G90 -> 20 | F90: ='Zoning Research'!Q90 -> 20 | G90: ='Zoning Research'!V90 -> 20 | H90: ='Zoning Research'!Z90 -> 20 | I90: ='Zoning Research'!AE90 -> 20 | J90: ='Zoning Research'!AF90 -> 100 | K90: ='Zoning Research'!AG90 -> 0 | L90: ='Zoning Research'!AH90 -> 0 | M90: ='Zoning Research'!AI90 -> AI Estimate | N90: 100 | O90: 100 | P90: =IF(J90="","",J90-AVERAGE(N90,O90)) -> 0
A91: Geneva | B91: IL | C91: 22000 | D91: A | E91: ='Zoning Research'!G91 -> 0 | F91: ='Zoning Research'!Q91 -> 0 | G91: ='Zoning Research'!V91 -> 0 | H91: ='Zoning Research'!Z91 -> 0 | I91: ='Zoning Research'!AE91 -> 0 | J91: ='Zoning Research'!AF91 -> 0 | K91: ='Zoning Research'!AG91 -> 0 | L91: ='Zoning Research'!AH91 -> 0 | M91: ='Zoning Research'!AI91 -> 0
A92: Yorkville | B92: IL | C92: 22000 | D92: A | E92: ='Zoning Research'!G92 -> 0 | F92: ='Zoning Research'!Q92 -> 0 | G92: ='Zoning Research'!V92 -> 0 | H92: ='Zoning Research'!Z92 -> 0 | I92: ='Zoning Research'!AE92 -> 0 | J92: ='Zoning Research'!AF92 -> 0 | K92: ='Zoning Research'!AG92 -> 0 | L92: ='Zoning Research'!AH92 -> 0 | M92: ='Zoning Research'!AI92 -> 0
A93: Darien | B93: IL | C93: 22000 | D93: A | E93: ='Zoning Research'!G93 -> 16 | F93: ='Zoning Research'!Q93 -> 16 | G93: ='Zoning Research'!V93 -> 16 | H93: ='Zoning Research'!Z93 -> 16 | I93: ='Zoning Research'!AE93 -> 16 | J93: ='Zoning Research'!AF93 -> 80 | K93: ='Zoning Research'!AG93 -> 0 | L93: ='Zoning Research'!AH93 -> 0 | M93: ='Zoning Research'!AI93 -> AI Estimate | N93: 65 | O93: 100 | P93: =IF(J93="","",J93-AVERAGE(N93,O93)) -> -2.5
A94: Villa Park | B94: IL | C94: 22000 | D94: A | E94: ='Zoning Research'!G94 -> 20 | F94: ='Zoning Research'!Q94 -> 20 | G94: ='Zoning Research'!V94 -> 20 | H94: ='Zoning Research'!Z94 -> 20 | I94: ='Zoning Research'!AE94 -> 20 | J94: ='Zoning Research'!AF94 -> 100 | K94: ='Zoning Research'!AG94 -> 0 | L94: ='Zoning Research'!AH94 -> 0 | M94: ='Zoning Research'!AI94 -> AI Estimate | N94: 100 | O94: 100 | P94: =IF(J94="","",J94-AVERAGE(N94,O94)) -> 0
A95: Bloomingdale | B95: IL | C95: 22000 | D95: A | E95: ='Zoning Research'!G95 -> 20 | F95: ='Zoning Research'!Q95 -> 20 | G95: ='Zoning Research'!V95 -> 20 | H95: ='Zoning Research'!Z95 -> 20 | I95: ='Zoning Research'!AE95 -> 20 | J95: ='Zoning Research'!AF95 -> 100 | K95: ='Zoning Research'!AG95 -> 0 | L95: ='Zoning Research'!AH95 -> 0 | M95: ='Zoning Research'!AI95 -> AI Estimate | N95: 100 | O95: 100 | P95: =IF(J95="","",J95-AVERAGE(N95,O95)) -> 0
A96: Carbondale | B96: IL | C96: 22000 | D96: A | E96: ='Zoning Research'!G96 -> 0 | F96: ='Zoning Research'!Q96 -> 0 | G96: ='Zoning Research'!V96 -> 0 | H96: ='Zoning Research'!Z96 -> 0 | I96: ='Zoning Research'!AE96 -> 0 | J96: ='Zoning Research'!AF96 -> 0 | K96: ='Zoning Research'!AG96 -> 0 | L96: ='Zoning Research'!AH96 -> 0 | M96: ='Zoning Research'!AI96 -> 0
A97: Homer Glen | B97: IL | C97: 21500 | D97: A | E97: ='Zoning Research'!G97 -> 20 | F97: ='Zoning Research'!Q97 -> 20 | G97: ='Zoning Research'!V97 -> 20 | H97: ='Zoning Research'!Z97 -> 20 | I97: ='Zoning Research'!AE97 -> 20 | J97: ='Zoning Research'!AF97 -> 100 | K97: ='Zoning Research'!AG97 -> 0 | L97: ='Zoning Research'!AH97 -> 0 | M97: ='Zoning Research'!AI97 -> AI Estimate | N97: 100 | O97: 100 | P97: =IF(J97="","",J97-AVERAGE(N97,O97)) -> 0
A98: Grayslake | B98: IL | C98: 21000 | D98: A | E98: ='Zoning Research'!G98 -> 20 | F98: ='Zoning Research'!Q98 -> 20 | G98: ='Zoning Research'!V98 -> 20 | H98: ='Zoning Research'!Z98 -> 20 | I98: ='Zoning Research'!AE98 -> 20 | J98: ='Zoning Research'!AF98 -> 100 | K98: ='Zoning Research'!AG98 -> 0 | L98: ='Zoning Research'!AH98 -> 0 | M98: ='Zoning Research'!AI98 -> AI Estimate | N98: 100 | O98: 100 | P98: =IF(J98="","",J98-AVERAGE(N98,O98)) -> 0
A99: Bensenville | B99: IL | C99: 21000 | D99: A | E99: ='Zoning Research'!G99 -> 20 | F99: ='Zoning Research'!Q99 -> 20 | G99: ='Zoning Research'!V99 -> 20 | H99: ='Zoning Research'!Z99 -> 20 | I99: ='Zoning Research'!AE99 -> 20 | J99: ='Zoning Research'!AF99 -> 100 | K99: ='Zoning Research'!AG99 -> 0 | L99: ='Zoning Research'!AH99 -> 0 | M99: ='Zoning Research'!AI99 -> AI Estimate | N99: 100 | O99: 100 | P99: =IF(J99="","",J99-AVERAGE(N99,O99)) -> 0
A100: Crest Hill | B100: IL | C100: 21000 | D100: A | E100: ='Zoning Research'!G100 -> 0 | F100: ='Zoning Research'!Q100 -> 0 | G100: ='Zoning Research'!V100 -> 0 | H100: ='Zoning Research'!Z100 -> 0 | I100: ='Zoning Research'!AE100 -> 0 | J100: ='Zoning Research'!AF100 -> 0 | K100: ='Zoning Research'!AG100 -> 0 | L100: ='Zoning Research'!AH100 -> 0 | M100: ='Zoning Research'!AI100 -> 0
...

Sheet Ground Truth
A1: Municipality | B1: State | C1: Use Type | D1: Our Score at Time | E1: Actual Outcome | F1: Date | G1: Predicted Correctly? | H1: Lesson Learned | I1: Score Adjustment Made?
A2: Naperville | B2: IL | C2: Drive-Thru Coffee | D2: 65 | E2: DENIED - City blocked Dutch Bros on Napier Blvd | F2: 2025 | G2: No | H2: Old AI score of 65 was too high. Real score ~38. City hostile to new DT coffee after 7 Brew approval. Saturation + political resistance not captured by zoning code analysis alone. | I2: Yes - dropped to 38
